xtesting/__init__.py
xtesting/ci/__init__.py
xtesting/ci/logging.debug.ini
xtesting/ci/logging.ini
xtesting/ci/run_tests.py
xtesting/ci/testcases.yaml
xtesting/ci/tier_builder.py
xtesting/ci/tier_handler.py
xtesting/core/__init__.py
xtesting/core/ansible.py
xtesting/core/behaveframework.py
xtesting/core/campaign.py
xtesting/core/feature.py
xtesting/core/pytest.py
xtesting/core/robotframework.py
xtesting/core/testcase.py
xtesting/core/unit.py
xtesting/core/vnf.py
xtesting/samples/HelloWorld.robot
xtesting/samples/__init__.py
xtesting/samples/first.py
xtesting/samples/fourth.py
xtesting/samples/helloworld.yml
xtesting/samples/second.py
xtesting/samples/features/hello.feature
xtesting/samples/features/steps/hello.py
xtesting/samples/mts/pause.xml
xtesting/samples/mts/test.xml
xtesting/tests/__init__.py
xtesting/tests/unit/__init__.py
xtesting/tests/unit/ci/__init__.py
xtesting/tests/unit/ci/test_run_tests.py
xtesting/tests/unit/ci/test_tier_builder.py
xtesting/tests/unit/ci/test_tier_handler.py
xtesting/tests/unit/core/__init__.py
xtesting/tests/unit/core/test_ansible.py
xtesting/tests/unit/core/test_behaveframework.py
xtesting/tests/unit/core/test_feature.py
xtesting/tests/unit/core/test_robotframework.py
xtesting/tests/unit/core/test_testcase.py
xtesting/tests/unit/core/test_unit.py
xtesting/tests/unit/core/test_vnf.py
xtesting/tests/unit/utils/__init__.py
xtesting/tests/unit/utils/test_decorators.py
xtesting/tests/unit/utils/test_env.py
xtesting/utils/__init__.py
xtesting/utils/config.py
xtesting/utils/constants.py
xtesting/utils/decorators.py
xtesting/utils/env.py
xtesting-1.0.0.dist-info/AUTHORS
xtesting-1.0.0.dist-info/LICENSE
xtesting-1.0.0.dist-info/METADATA
xtesting-1.0.0.dist-info/WHEEL
xtesting-1.0.0.dist-info/entry_points.txt
xtesting-1.0.0.dist-info/pbr.json
xtesting-1.0.0.dist-info/top_level.txt
xtesting-1.0.0.dist-info/RECORD
