Metadata-Version: 2.1
Name: xtesting
Version: 1.0.0
Summary: OPNFV reference testing framework
Home-page: https://wiki.opnfv.org/display/functest
Author: OPNFV
Author-email: opnfv-tech-discuss@lists.opnfv.org
Classifier: Intended Audience :: Information Technology
Classifier: Intended Audience :: System Administrators
Classifier: License :: OSI Approved :: Apache Software License
Classifier: Operating System :: POSIX :: Linux
Classifier: Programming Language :: Python
Classifier: Programming Language :: Python :: 3
Classifier: Programming Language :: Python :: 3.8
Requires-Python: >=3.9
License-File: LICENSE
License-File: AUTHORS
Requires-Dist: pbr !=2.1.0
Requires-Dist: stevedore !=3.0.0
Requires-Dist: PyYAML
Requires-Dist: requests !=2.20.0,!=2.24.0
Requires-Dist: robotframework >=4.0
Requires-Dist: behave >=1.2.6
Requires-Dist: mock !=4.0.0,!=4.0.1
Requires-Dist: PrettyTable !=3.4.0
Requires-Dist: python-subunit
Requires-Dist: os-testr
Requires-Dist: junitxml
Requires-Dist: boto3
Requires-Dist: lxml !=3.7.0
Requires-Dist: ansible-runner !=1.3.5
Requires-Dist: pytest
Requires-Dist: pytest-html
Requires-Dist: enum34 ; (python_version=='2.7' or python_version=='2.6' or python_version=='3.3')
Requires-Dist: behave-html-formatter >=0.9.4 ; (python_version>='3.6')
